minecraft_render/__init__.py
minecraft_render/__main__.py
minecraft_render/__npm_version__.py
minecraft_render/js_module.py
minecraft_render/py.typed
minecraft_render/types/__init__.py
minecraft_render/types/dataset/Loader.py
minecraft_render/types/dataset/RenderClass.py
minecraft_render/types/dataset/__init__.py
minecraft_render/types/dataset/types.py
minecraft_render/types/dataset/utils.py
minecraft_render/types/utils/__init__.py
minecraft_render/types/utils/resource.py
minecraft_render/types/utils/types.py
minecraft_render-2.0.0a6.dist-info/METADATA
minecraft_render-2.0.0a6.dist-info/WHEEL
minecraft_render-2.0.0a6.dist-info/licenses/LICENSE.md
minecraft_render-2.0.0a6.dist-info/RECORD
