Metadata-Version: 2.1
Name: minecraft-render
Version: 2.0.0a6
Summary: Minecraft block/texture rendering with node.js and Python via JSPyBridge.
Author-email: object-Object <object@objectobject.ca>, co3moz <doganderya59@gmail.com>
License: MIT License
License-File: LICENSE.md
Requires-Python: >=3.11
Requires-Dist: importlib-resources~=6.0
Requires-Dist: javascript~=1!1.0
Provides-Extra: dev
Requires-Dist: black==23.7.0; extra == 'dev'
Requires-Dist: hatch; extra == 'dev'
Requires-Dist: isort==5.12.0; extra == 'dev'
